{"type":"PR","pr":{"number":71,"head":"6426b3775e1ad53b1a1f5a1bee1a2239e78d0be2"},"user":"adtadmin","status":"pending_publish","branch":"cms/2-stretnutie-riaditeľov-divadiel-na-divadelnej-nitre","collection":"oznamy","title":"2. stretnutie riaditeľov divadiel na Divadelnej Nitre","description":"No Description!","objects":{"entry":{"path":"site/content/oznamy/2-stretnutie-riaditeľov-divadiel-na-divadelnej-nitre.md","sha":"f76f356030868bd26b5b4377e4b43cf42a3c3722"},"files":[]},"timeStamp":"2019-10-16T12:22:39.081Z"}